anam_python_sdk/__init__.py
anam_python_sdk/api/client.py
anam_python_sdk/api/examples/__init__.py
anam_python_sdk/api/examples/gameplay.py
anam_python_sdk/api/examples/qa.py
anam_python_sdk/api/examples/rag.py
anam_python_sdk/api/examples/training.py
anam_python_sdk/api/model.py
anam_python_sdk/api/prompts/__init__.py
anam_python_sdk/api/prompts/defaults.py
anam_python_sdk/chat/handlers/__init__.py
anam_python_sdk/chat/handlers/audio.py
anam_python_sdk/chat/handlers/data.py
anam_python_sdk/chat/handlers/video.py
anam_python_sdk/chat/main.py
anam_python_sdk/chat/session.py
anam_python_sdk/chat/signaling.py
anam_python_sdk/chat/streaming.py
anam_python_sdk/chat/test.py
anam_python_sdk-0.4.0.dist-info/METADATA
anam_python_sdk-0.4.0.dist-info/WHEEL
anam_python_sdk-0.4.0.dist-info/RECORD
