Metadata-Version: 2.1
Name: anam-python-sdk
Version: 0.4.0
Summary: An unofficial package to interact with Anam's Avatar engine.
Home-page: https://www.anam.ai
License: MIT
Author: Quinten Rosseel
Author-email: quinten@anam.ai
Requires-Python: >=3.10,<4.0
Classifier: License :: OSI Approved :: MIT License
Classifier: Programming Language :: Python :: 3
Classifier: Programming Language :: Python :: 3.10
Classifier: Programming Language :: Python :: 3.11
Classifier: Programming Language :: Python :: 3.12
Provides-Extra: livekit
Provides-Extra: webrtc
Requires-Dist: python-dotenv (>=1.0.1,<2.0.0)
Requires-Dist: requests (>=2.32.3,<3.0.0)
Project-URL: Repository, https://github.com/anam-org/python-sdk
